{"makerCommission":0,"takerCommission":0,"buyerCommission":0,"sellerCommission":0,"canTrade":true,"canWithdraw":true,"canDeposit":true,"updateTime":1741900472601,"balances":[{"asset":"1000CAT","free":"18446","locked":"0"},{"asset":"1000CHEEMS","free":"18446","locked":"0"},{"asset":"1000SATS","free":"18446","locked":"0"},{"asset":"1INCH","free":"2144","locked":"0"},{"asset":"1MBABYDOGE","free":"18446","locked":"0"},{"asset":"AAVE","free":"2","locked":"0"},{"asset":"ACA","free":"11879","locked":"0"},{"asset":"ACE","free":"633","locked":"0"},{"asset":"ACH","free":"18446","locked":"0"},{"asset":"ACM","free":"522","locked":"0"},{"asset":"ACT","free":"2574","locked":"0"},{"asset":"ACX","free":"2041","locked":"0"},{"asset":"ADA","free":"504","locked":"0"},{"asset":"ADX","free":"4241","locked":"0"},{"asset":"AERGO","free":"6887","locked":"0"},{"asset":"AEUR","free":"499","locked":"0"},{"asset":"AEVO","free":"3716","locked":"0"},{"asset":"AGLD","free":"387","locked":"0"},{"asset":"AI","free":"2409","locked":"0"},{"asset":"AIXBT","free":"3123","locked":"0"},{"asset":"ALCX","free":"46","locked":"0"},{"asset":"ALGO","free":"2011","locked":"0"},{"asset":"ALICE","free":"863","locked":"0"},{"asset":"ALPACA","free":"7135","locked":"0"},{"asset":"ALPHA","free":"12337","locked":"0"},{"asset":"ALPINE","free":"535","locked":"0"},{"asset":"ALT","free":"13075","locked":"0"},{"asset":"AMP","free":"18446","locked":"0"},{"asset":"ANIME","free":"18446","locked":"0"},{"asset":"ANKR","free":"18446","locked":"0"},{"asset":"APE","free":"892","locked":"0"},{"asset":"API3","free":"749","locked":"0"},{"asset":"APT","free":"84","locked":"0"},{"asset":"AR","free":"66","locked":"0"},{"asset":"ARB","free":"1257","locked":"0"},{"asset":"ARDR","free":"7970","locked":"0"},{"asset":"ARK","free":"1432","locked":"0"},{"asset":"ARKM","free":"895","locked":"0"},{"asset":"ARPA","free":"16152","locked":"0"},{"asset":"ARS","free":"18466","locked":"0"},{"asset":"ASR","free":"385","locked":"0"},{"asset":"AST","free":"9655","locked":"0"},{"asset":"ASTR","free":"14618","locked":"0"},{"asset":"ATA","free":"8882","locked":"0"},{"asset":"ATM","free":"371","locked":"0"},{"asset":"ATOM","free":"118","locked":"0"},{"asset":"AUCTION","free":"42","locked":"0"},{"asset":"AUDIO","free":"6014","locked":"0"},{"asset":"AVA","free":"851","locked":"0"},{"asset":"AVAX","free":"23","locked":"0"},{"asset":"AXL","free":"1275","locked":"0"},{"asset":"AXS","free":"142","locked":"0"},{"asset":"BADGER","free":"153","locked":"0"},{"asset":"BAKE","free":"3577","locked":"0"},{"asset":"BAL","free":"299","locked":"0"},{"asset":"BANANA","free":"34","locked":"0"},{"asset":"BAND","free":"556","locked":"0"},{"asset":"BAR","free":"283","locked":"0"},{"asset":"BAT","free":"3117","locked":"0"},{"asset":"BB","free":"3614","locked":"0"},{"asset":"BCH","free":"1","locked":"0"},{"asset":"BEAMX","free":"18446","locked":"0"},{"asset":"BEL","free":"568","locked":"0"},{"asset":"BERA","free":"73","locked":"0"},{"asset":"BETA","free":"18446","locked":"0"},{"asset":"BICO","free":"3622","locked":"0"},{"asset":"BIFI","free":"2","locked":"0"},{"asset":"BIO","free":"5007","locked":"0"},{"asset":"BLUR","free":"4204","locked":"0"},{"asset":"BNB","free":"1","locked":"0"},{"asset":"BNSOL","free":"3","locked":"0"},{"asset":"BNT","free":"1106","locked":"0"},{"asset":"BNX","free":"594","locked":"0"},{"asset":"BOME","free":"18446","locked":"0"},{"asset":"BONK","free":"18446","locked":"0"},{"asset":"BRL","free":"97","locked":"0"},{"asset":"BSW","free":"13821","locked":"0"},{"asset":"BTC","free":"1","locked":"0"},{"asset":"BTTC","free":"18446","locked":"0"},{"asset":"BURGER","free":"2242","locked":"0"},{"asset":"C98","free":"6818","locked":"0"},{"asset":"CAKE","free":"281","locked":"0"},{"asset":"CATI","free":"3325","locked":"0"},{"asset":"CELO","free":"1327","locked":"0"},{"asset":"CELR","free":"18446","locked":"0"},{"asset":"CETUS","free":"5054","locked":"0"},{"asset":"CFX","free":"4963","locked":"0"},{"asset":"CGPT","free":"4289","locked":"0"},{"asset":"CHESS","free":"5023","locked":"0"},{"asset":"CHR","free":"4534","locked":"0"},{"asset":"CHZ","free":"10293","locked":"0"},{"asset":"CITY","free":"445","locked":"0"},{"asset":"CKB","free":"18446","locked":"0"},{"asset":"COMBO","free":"2578","locked":"0"},{"asset":"COMP","free":"9","locked":"0"},{"asset":"COOKIE","free":"2807","locked":"0"},{"asset":"COP","free":"18466","locked":"0"},{"asset":"COS","free":"18446","locked":"0"},{"asset":"COTI","free":"6240","locked":"0"},{"asset":"COW","free":"1630","locked":"0"},{"asset":"CREAM","free":"81","locked":"0"},{"asset":"CRV","free":"1137","locked":"0"},{"asset":"CTK","free":"1343","locked":"0"},{"asset":"CTSI","free":"6105","locked":"0"},{"asset":"CTXC","free":"3276","locked":"0"},{"asset":"CVC","free":"4707","locked":"0"},{"asset":"CVX","free":"221","locked":"0"},{"asset":"CYBER","free":"359","locked":"0"},{"asset":"CZK","free":"18466","locked":"0"},{"asset":"D","free":"7710","locked":"0"},{"asset":"DAI","free":"10000","locked":"0"},{"asset":"DASH","free":"20","locked":"0"},{"asset":"DATA","free":"18446","locked":"0"},{"asset":"DCR","free":"41","locked":"0"},{"asset":"DEGO","free":"324","locked":"0"},{"asset":"DENT","free":"18446","locked":"0"},{"asset":"DEXE","free":"25","locked":"0"},{"asset":"DF","free":"6902","locked":"0"},{"asset":"DGB","free":"18446","locked":"0"},{"asset":"DIA","free":"1106","locked":"0"},{"asset":"DODO","free":"6361","locked":"0"},{"asset":"DOGE","free":"2463","locked":"0"},{"asset":"DOGS","free":"18446","locked":"0"},{"asset":"DOT","free":"113","locked":"0"},{"asset":"DUSK","free":"4430","locked":"0"},{"asset":"DYDX","free":"773","locked":"0"},{"asset":"DYM","free":"1417","locked":"0"},{"asset":"EDU","free":"2659","locked":"0"},{"asset":"EGLD","free":"22","locked":"0"},{"asset":"EIGEN","free":"339","locked":"0"},{"asset":"ELF","free":"2029","locked":"0"},{"asset":"ENA","free":"1314","locked":"0"},{"asset":"ENJ","free":"4825","locked":"0"},{"asset":"ENS","free":"23","locked":"0"},{"asset":"EOS","free":"920","locked":"0"},{"asset":"ERN","free":"289","locked":"0"},{"asset":"ETC","free":"25","locked":"0"},{"asset":"ETH","free":"1","locked":"0"},{"asset":"ETHFI","free":"585","locked":"0"},{"asset":"EUR","free":"467","locked":"0"},{"asset":"EURI","free":"467","locked":"0"},{"asset":"FARM","free":"17","locked":"0"},{"asset":"FDUSD","free":"10000","locked":"0"},{"asset":"FET","free":"821","locked":"0"},{"asset":"FIDA","free":"4118","locked":"0"},{"asset":"FIL","free":"162","locked":"0"},{"asset":"FIO","free":"18446","locked":"0"},{"asset":"FIRO","free":"449","locked":"0"},{"asset":"FIS","free":"2661","locked":"0"},{"asset":"FLM","free":"14577","locked":"0"},{"asset":"FLOKI","free":"18446","locked":"0"},{"asset":"FLOW","free":"1116","locked":"0"},{"asset":"FLUX","free":"1554","locked":"0"},{"asset":"FORTH","free":"164","locked":"0"},{"asset":"FTT","free":"330","locked":"0"},{"asset":"FUN","free":"18446","locked":"0"},{"asset":"FXS","free":"319","locked":"0"},{"asset":"G","free":"18446","locked":"0"},{"asset":"GALA","free":"18446","locked":"0"},{"asset":"GAS","free":"155","locked":"0"},{"asset":"GHST","free":"1090","locked":"0"},{"asset":"GLM","free":"1580","locked":"0"},{"asset":"GLMR","free":"4812","locked":"0"},{"asset":"GMT","free":"9587","locked":"0"},{"asset":"GMX","free":"31","locked":"0"},{"asset":"GNO","free":"3","locked":"0"},{"asset":"GNS","free":"339","locked":"0"},{"asset":"GPS","free":"7550","locked":"0"},{"asset":"GRT","free":"4616","locked":"0"},{"asset":"GTC","free":"1272","locked":"0"},{"asset":"HARD","free":"3415","locked":"0"},{"asset":"HBAR","free":"1967","locked":"0"},{"asset":"HEI","free":"1050","locked":"0"},{"asset":"HFT","free":"5865","locked":"0"},{"asset":"HIFI","free":"1379","locked":"0"},{"asset":"HIGH","free":"663","locked":"0"},{"asset":"HIVE","free":"1878","locked":"0"},{"asset":"HMSTR","free":"18446","locked":"0"},{"asset":"HOOK","free":"2896","locked":"0"},{"asset":"HOT","free":"18446","locked":"0"},{"asset":"ICP","free":"80","locked":"0"},{"asset":"ICX","free":"4500","locked":"0"},{"asset":"ID","free":"2074","locked":"0"},{"asset":"IDEX","free":"16062","locked":"0"},{"asset":"ILV","free":"30","locked":"0"},{"asset":"IMX","free":"788","locked":"0"},{"asset":"INJ","free":"42","locked":"0"},{"asset":"IO","free":"462","locked":"0"},{"asset":"IOST","free":"18446","locked":"0"},{"asset":"IOTA","free":"2289","locked":"0"},{"asset":"IOTX","free":"18446","locked":"0"},{"asset":"IQ","free":"18446","locked":"0"},{"asset":"JASMY","free":"18446","locked":"0"},{"asset":"JOE","free":"2493","locked":"0"},{"asset":"JPY","free":"18466","locked":"0"},{"asset":"JST","free":"15374","locked":"0"},{"asset":"JTO","free":"191","locked":"0"},{"asset":"JUP","free":"772","locked":"0"},{"asset":"JUV","free":"421","locked":"0"},{"asset":"KAIA","free":"4224","locked":"0"},{"asset":"KAITO","free":"272","locked":"0"},{"asset":"KAVA","free":"1158","locked":"0"},{"asset":"KDA","free":"993","locked":"0"},{"asset":"KMD","free":"2864","locked":"0"},{"asset":"KNC","free":"1359","locked":"0"},{"asset":"KSM","free":"27","locked":"0"},{"asset":"LAYER","free":"562","locked":"0"},{"asset":"LAZIO","free":"471","locked":"0"},{"asset":"LDO","free":"435","locked":"0"},{"asset":"LEVER","free":"18446","locked":"0"},{"asset":"LINA","free":"18446","locked":"0"},{"asset":"LINK","free":"31","locked":"0"},{"asset":"LISTA","free":"2704","locked":"0"},{"asset":"LOKA","free":"4180","locked":"0"},{"asset":"LPT","free":"80","locked":"0"},{"asset":"LQTY","free":"635","locked":"0"},{"asset":"LRC","free":"4385","locked":"0"},{"asset":"LSK","free":"824","locked":"0"},{"asset":"LTC","free":"4","locked":"0"},{"asset":"LTO","free":"7337","locked":"0"},{"asset":"LUMIA","free":"1105","locked":"0"},{"asset":"LUNA","free":"2354","locked":"0"},{"asset":"LUNC","free":"18446","locked":"0"},{"asset":"MAGIC","free":"2779","locked":"0"},{"asset":"MANA","free":"1753","locked":"0"},{"asset":"MANTA","free":"1619","locked":"0"},{"asset":"MASK","free":"225","locked":"0"},{"asset":"MAV","free":"7089","locked":"0"},{"asset":"MBL","free":"18446","locked":"0"},{"asset":"MBOX","free":"5087","locked":"0"},{"asset":"MDT","free":"18063","locked":"0"},{"asset":"ME","free":"427","locked":"0"},{"asset":"MEME","free":"18446","locked":"0"},{"asset":"METIS","free":"24","locked":"0"},{"asset":"MINA","free":"1697","locked":"0"},{"asset":"MKR","free":"1","locked":"0"},{"asset":"MLN","free":"47","locked":"0"},{"asset":"MOVE","free":"1216","locked":"0"},{"asset":"MOVR","free":"74","locked":"0"},{"asset":"MTL","free":"613","locked":"0"},{"asset":"MXN","free":"18466","locked":"0"},{"asset":"NEAR","free":"172","locked":"0"},{"asset":"NEIRO","free":"18446","locked":"0"},{"asset":"NEO","free":"55","locked":"0"},{"asset":"NEXO","free":"429","locked":"0"},{"asset":"NFP","free":"5184","locked":"0"},{"asset":"NKN","free":"9690","locked":"0"},{"asset":"NMR","free":"53","locked":"0"},{"asset":"NOT","free":"18446","locked":"0"},{"asset":"NTRN","free":"3276","locked":"0"},{"asset":"NULS","free":"3135","locked":"0"},{"asset":"OG","free":"139","locked":"0"},{"asset":"OGN","free":"7486","locked":"0"},{"asset":"OM","free":"69","locked":"0"},{"asset":"OMNI","free":"119","locked":"0"},{"asset":"ONE","free":"18446","locked":"0"},{"asset":"ONG","free":"2147","locked":"0"},{"asset":"ONT","free":"3159","locked":"0"},{"asset":"OP","free":"520","locked":"0"},{"asset":"ORCA","free":"294","locked":"0"},{"asset":"ORDI","free":"46","locked":"0"},{"asset":"OSMO","free":"1753","locked":"0"},{"asset":"OXT","free":"6074","locked":"0"},{"asset":"PAXG","free":"1","locked":"0"},{"asset":"PDA","free":"18446","locked":"0"},{"asset":"PENDLE","free":"199","locked":"0"},{"asset":"PENGU","free":"18446","locked":"0"},{"asset":"PEOPLE","free":"18446","locked":"0"},{"asset":"PEPE","free":"18446","locked":"0"},{"asset":"PERP","free":"1258","locked":"0"},{"asset":"PHA","free":"3761","locked":"0"},{"asset":"PHB","free":"740","locked":"0"},{"asset":"PIVX","free":"3022","locked":"0"},{"asset":"PIXEL","free":"10589","locked":"0"},{"asset":"PLN","free":"18466","locked":"0"},{"asset":"PNUT","free":"2510","locked":"0"},{"asset":"POL","free":"1976","locked":"0"},{"asset":"POLYX","free":"3368","locked":"0"},{"asset":"POND","free":"18446","locked":"0"},{"asset":"PORTAL","free":"4359","locked":"0"},{"asset":"PORTO","free":"472","locked":"0"},{"asset":"POWR","free":"2762","locked":"0"},{"asset":"PROM","free":"74","locked":"0"},{"asset":"PROS","free":"1502","locked":"0"},{"asset":"PSG","free":"218","locked":"0"},{"asset":"PUNDIX","free":"1579","locked":"0"},{"asset":"PYR","free":"307","locked":"0"},{"asset":"PYTH","free":"2737","locked":"0"},{"asset":"QI","free":"18446","locked":"0"},{"asset":"QKC","free":"18446","locked":"0"},{"asset":"QNT","free":"5","locked":"0"},{"asset":"QTUM","free":"212","locked":"0"},{"asset":"QUICK","free":"18446","locked":"0"},{"asset":"RAD","free":"661","locked":"0"},{"asset":"RARE","free":"10049","locked":"0"},{"asset":"RAY","free":"226","locked":"0"},{"asset":"RDNT","free":"18172","locked":"0"},{"asset":"RED","free":"593","locked":"0"},{"asset":"REI","free":"17260","locked":"0"},{"asset":"RENDER","free":"135","locked":"0"},{"asset":"REQ","free":"4440","locked":"0"},{"asset":"REZ","free":"18446","locked":"0"},{"asset":"RIF","free":"10902","locked":"0"},{"asset":"RLC","free":"401","locked":"0"},{"asset":"RON","free":"18466","locked":"0"},{"asset":"RONIN","free":"539","locked":"0"},{"asset":"ROSE","free":"13719","locked":"0"},{"asset":"RPL","free":"83","locked":"0"},{"asset":"RSR","free":"18446","locked":"0"},{"asset":"RUNE","free":"411","locked":"0"},{"asset":"RVN","free":"18446","locked":"0"},{"asset":"S","free":"865","locked":"0"},{"asset":"SAGA","free":"1216","locked":"0"},{"asset":"SAND","free":"1620","locked":"0"},{"asset":"SANTOS","free":"200","locked":"0"},{"asset":"SC","free":"18446","locked":"0"},{"asset":"SCR","free":"1075","locked":"0"},{"asset":"SCRT","free":"2426","locked":"0"},{"asset":"SEI","free":"2157","locked":"0"},{"asset":"SFP","free":"837","locked":"0"},{"asset":"SHELL","free":"1416","locked":"0"},{"asset":"SHIB","free":"18446","locked":"0"},{"asset":"SKL","free":"17170","locked":"0"},{"asset":"SLF","free":"2249","locked":"0"},{"asset":"SLP","free":"18446","locked":"0"},{"asset":"SNT","free":"18016","locked":"0"},{"asset":"SNX","free":"533","locked":"0"},{"asset":"SOL","free":"3","locked":"0"},{"asset":"SOLV","free":"11525","locked":"0"},{"asset":"SPELL","free":"18446","locked":"0"},{"asset":"SSV","free":"51","locked":"0"},{"asset":"STEEM","free":"3487","locked":"0"},{"asset":"STG","free":"2211","locked":"0"},{"asset":"STORJ","free":"1648","locked":"0"},{"asset":"STPT","free":"6364","locked":"0"},{"asset":"STRAX","free":"11029","locked":"0"},{"asset":"STRK","free":"2751","locked":"0"},{"asset":"STX","free":"691","locked":"0"},{"asset":"SUI","free":"198","locked":"0"},{"asset":"SUN","free":"18446","locked":"0"},{"asset":"SUPER","free":"831","locked":"0"},{"asset":"SUSHI","free":"685","locked":"0"},{"asset":"SXP","free":"2417","locked":"0"},{"asset":"SYN","free":"1999","locked":"0"},{"asset":"SYS","free":"9271","locked":"0"},{"asset":"T","free":"18446","locked":"0"},{"asset":"TAO","free":"1","locked":"0"},{"asset":"TFUEL","free":"12057","locked":"0"},{"asset":"THE","free":"1170","locked":"0"},{"asset":"THETA","free":"464","locked":"0"},{"asset":"TIA","free":"148","locked":"0"},{"asset":"TKO","free":"2382","locked":"0"},{"asset":"TLM","free":"18446","locked":"0"},{"asset":"TNSR","free":"1150","locked":"0"},{"asset":"TON","free":"164","locked":"0"},{"asset":"TRB","free":"16","locked":"0"},{"asset":"TROY","free":"18446","locked":"0"},{"asset":"TRU","free":"12287","locked":"0"},{"asset":"TRUMP","free":"37","locked":"0"},{"asset":"TRX","free":"2059","locked":"0"},{"asset":"TRY","free":"18466","locked":"0"},{"asset":"TST","free":"7033","locked":"0"},{"asset":"TURBO","free":"18446","locked":"0"},{"asset":"TUSD","free":"10000","locked":"0"},{"asset":"TWT","free":"482","locked":"0"},{"asset":"UAH","free":"18466","locked":"0"},{"asset":"UFT","free":"4283","locked":"0"},{"asset":"UMA","free":"371","locked":"0"},{"asset":"UNI","free":"67","locked":"0"},{"asset":"USDC","free":"10000","locked":"0"},{"asset":"USDP","free":"499","locked":"0"},{"asset":"USDT","free":"10000","locked":"0"},{"asset":"USTC","free":"18446","locked":"0"},{"asset":"USUAL","free":"2484","locked":"0"},{"asset":"UTK","free":"11707","locked":"0"},{"asset":"VANA","free":"79","locked":"0"},{"asset":"VANRY","free":"14744","locked":"0"},{"asset":"VELODROME","free":"8156","locked":"0"},{"asset":"VET","free":"17310","locked":"0"},{"asset":"VIB","free":"11104","locked":"0"},{"asset":"VIC","free":"2003","locked":"0"},{"asset":"VIDT","free":"18446","locked":"0"},{"asset":"VOXEL","free":"5751","locked":"0"},{"asset":"VTHO","free":"18446","locked":"0"},{"asset":"W","free":"4564","locked":"0"},{"asset":"WAN","free":"4155","locked":"0"},{"asset":"WAXP","free":"18313","locked":"0"},{"asset":"WBETH","free":"1","locked":"0"},{"asset":"WBTC","free":"1","locked":"0"},{"asset":"WIF","free":"855","locked":"0"},{"asset":"WIN","free":"18446","locked":"0"},{"asset":"WING","free":"168","locked":"0"},{"asset":"WLD","free":"509","locked":"0"},{"asset":"WOO","free":"5032","locked":"0"},{"asset":"XAI","free":"6505","locked":"0"},{"asset":"XEC","free":"18446","locked":"0"},{"asset":"XLM","free":"1644","locked":"0"},{"asset":"XNO","free":"405","locked":"0"},{"asset":"XRP","free":"201","locked":"0"},{"asset":"XTZ","free":"655","locked":"0"},{"asset":"XVG","free":"18446","locked":"0"},{"asset":"XVS","free":"79","locked":"0"},{"asset":"YFI","free":"1","locked":"0"},{"asset":"YGG","free":"2260","locked":"0"},{"asset":"ZAR","free":"18466","locked":"0"},{"asset":"ZEC","free":"13","locked":"0"},{"asset":"ZEN","free":"43","locked":"0"},{"asset":"ZIL","free":"18446","locked":"0"},{"asset":"ZK","free":"5881","locked":"0"},{"asset":"ZRO","free":"223","locked":"0"},{"asset":"ZRX","free":"1780","locked":"0"}]}